depends/__init__.py
depends/hash_user.py
depends/validate.py
dong_api/__init__.py
dong_api/auth.py
dong_api/model_user.py
dong_api/users.py
dong_api/depends/__init__.py
dong_api/depends/hash_user.py
dong_api/depends/validate.py
models/__init__.py
models/user_schema.py
routes/__init__.py
routes/users.py
utils/__init__.py
utils/auth.py
dong_user_api-0.1.1.dist-info/METADATA
dong_user_api-0.1.1.dist-info/WHEEL
dong_user_api-0.1.1.dist-info/top_level.txt
dong_user_api-0.1.1.dist-info/RECORD
